{
    "categories": [
      { "id": 1, "name": "ultimos" },
      { "id": 2, "name": "Remeras" },
      { "id": 3, "name": "tops" },
      { "id": 4, "name": "buzos" },
      { "id": 5, "name": "pantalones" },
      { "id": 6, "name": "corset"} 
      
    ],


    "products": [

      {		
        "id": 	1	,
        "name": 	"Vestido MOTOMAMI ONE",	
        "description": 	"Vestido de Tela Modal Soft",	
        "price": 16500,	
        "image": 	"VestidoMotoONE.jpeg"	,
        "imageDetail": [		
          { "id": 1, "url": "VestidoMotoONE.jpeg" },	
          { "id": 2, "url": "VestidoMotoONE.jpeg" },	
          { "id": 3, "url": "caracterisitcas.jpeg" }	
          ],	
        "categoryId": 	1	
        },	
        {	
      "id": 	2,
      "name": 	"Vestido MOTOMAMI TWO",
      "description": 	"Vestido de Tela Modal Soft",
      "price": 	16500,
      "image": 	"VestidoMotoTWO.jpeg",
      "imageDetail": [	
      	{ "id": 1, "url": "VestidoMotoTWO.jpeg" },
      	{ "id": 2, "url": "VestidoMotoTWO2.jpeg" },
      	{ "id": 3, "url": "caracterisitcas.jpeg" }
      	],
      "categoryId": 	1
      },	



      {	
      "id": 	3,
      "name": 	"Vestido MOTOMAMI THREE",
      "description": 	"Vestido de Tela Modal Soft",
      "price": 	16500,
      "image": 	"VestidoMotoTHREE.jpeg",
      "imageDetail": [	
      	{ "id": 1, "url": "VestidoMotoTHREE.jpeg" },
      	{ "id": 2, "url": "VestidoMotoTHREE2.jpeg" },
      	{ "id": 3, "url": "caracterisitcas.jpeg" }
      	],
      "categoryId": 	1
      },	



      {	
      "id": 	4,
      "name": 	"Vestido Double Dragon 🐉🐉",
      "description": 	"Vestido de Tela Modal Soft",
      "price": 	10500,
      "image": 	 "VestidoDragon.jpeg",
      "imageDetail": [	
      	{ "id": 1, "url": "VestidoDragon.jpeg" },
      	{ "id": 2, "url": "VestidoDragon2.jpeg" },
      	{ "id": 3, "url": "caracterisitcas.jpeg" }
      	],
      "categoryId": 	1
      },	

     {	
      "id": 	5,
      "name": 	"remera dragon",
      "description": 	"Remera de Algodon",
      "price": 	5850,
      "image": 	"RemeraDragon.jpeg",
      "imageDetail": [	
      	{ "id": 1, "url": "RemeraDragon.jpeg" },
      	{ "id": 2, "url": "RemeraDragon.jpeg" },
      	{ "id": 3, "url": "RemeraDragon.jpeg" }
      	],
      "categoryId": 	1
      },		

      {	
      "id": 	6,
      "name": 	"Vestudi NUDE",
      "description": 	"Vestido de Tela Modal Soft",
      "price": 	16500,
      "image": 	"VestidoNude.jpeg",
      "imageDetail": [	
      	{ "id": 1, "url": "VestidoNude.jpeg" },
      	{ "id": 2, "url": "VestidoNude2.jpeg" },
      	{ "id": 3, "url": "caracterisitcas.jpeg" }
      	],
      "categoryId": 	1
      },	

      {		
        "id": 	10	,
        "name": 	"CORSET IN COLORS 💜",	
        "description": 	"talles del S al XXL"	,
        "price": 	15450	,
        "image": 	"CORSETCOLORS1.jpeg",	
        "imageDetail": [		
          { "id": 1, "url": "CORSETCOLORS1.jpeg" },	
          { "id": 2, "url": "CORSETCOLORS11.jpeg" },	
          { "id": 3, "url": "CORSETCOLORS6.jpeg" }	
          ],	
        "categoryId": 	6	
        },		
            
            
        {		
        "id": 	11	,
        "name": 	"CORSET IN COLORS 🧡",	
        "description": 	"talles del S al XXL",
        "price": 	15450	,
        "image": 	"CORSETCOLORS2.jpeg",	
        "imageDetail": [		
          { "id": 1, "url": "CORSETCOLORS2.jpeg" },	
          { "id": 2, "url": "CORSETCOLORS22.jpeg" },	
          { "id": 3, "url": "CORSETCOLORS6.jpeg" }	
          ],	
        "categoryId": 	6	
        },		
            
            
        {		
        "id": 	11	,
        "name": 	"CORSET IN COLORS 💚",	
        "description": 	"talles del S al XXL"	,
        "price": 	15450	,
        "image": 	"CORSETCOLORS3.jpeg",	
        "imageDetail": [		
          { "id": 1, "url": "CORSETCOLORS3.jpeg" },	
          { "id": 2, "url": "CORSETCOLORS33.jpeg" },	
          { "id": 3, "url": "CORSETCOLORS6.jpeg" }	
          ],	
        "categoryId": 	6	
        },		
            
            
            
        {		
        "id": 	12	,
        "name": 	"CORSET IN COLORS 🤎",	
        "description": 	"talles del S al XXL"	,
        "price": 	15450	,
        "image": 	"CORSETCOLORS4.jpeg",	
        "imageDetail": [		
          { "id": 1, "url": "CORSETCOLORS4.jpeg" },	
          { "id": 2, "url": "CORSETCOLORS44.jpeg" },	
          { "id": 3, "url": "CORSETCOLORS6.jpeg" }	
          ],	
        "categoryId": 	6	
        },		
            
            
        {		
        "id": 	13	,
        "name": 	"CORSET IN COLORS ❤️",	
        "description": 	"talles del S al XXL"	,
        "price": 	15450	,
        "image": 	"CORSETCOLORS5.jpeg",	
        "imageDetail": [		
          { "id": 1, "url": "CORSETCOLORS5.jpeg" },	
          { "id": 2, "url": "CORSETCOLORS55.jpeg" },	
          { "id": 3, "url": "CORSETCOLORS6.jpeg" }	
          ],	
        "categoryId": 	6	
        },	
        
          {		
        "id": 	20	,
        "name": 	"REMERA MICROTUL",	
        "description": 	"XL"	,
        "price": 	13750	,
        "image": 	"MICROTUL.jpeg",	
        "imageDetail": [		
        	{ "id": 1, "url": "MICROTUL.jpeg" },	
        	{ "id": 2, "url": "MICROTUL2.jpeg" },	
        	{ "id": 3, "url": "MICROTUL3.jpeg" }	
        	],	
        "categoryId": 	2	
        },		


        {		
        "id": 	21	,
        "name": 	"REMERA ANDROIDL",	
        "description": 	"DEL TALLE M AL XL"	,
        "price": 	14000	,
        "image": 	"REMERAANDROID.jpeg",	
        "imageDetail": [		
        	{ "id": 1, "url": "REMERAANDROID.jpeg" },	
        	{ "id": 2, "url": "REMERAANDROID1.jpeg" },	
        	{ "id": 3, "url": "REMERAANDROID2.jpeg" }	
        	],	
        "categoryId": 	2	
        },		



        {		
        "id": 	22	,
        "name": 	"POLERA ORGANIC",	
        "description": 	"DEL TALLE S AL XL"	,
        "price": 	13900	,
        "image": 	"POLERAORGANIC.jpeg",	
        "imageDetail": [		
        	{ "id": 1, "url": "POLERAORGANIC.jpeg" },	
        	{ "id": 2, "url": "POLERAORGANIC1.jpeg" },	
        	{ "id": 3, "url": "POLERAORGANIC2.jpeg" }	
        	],	
        "categoryId": 	2	
        },		


        {		
        "id": 	23	,
        "name": 	"REMERA MONS",	
        "description": 	"Black or White"	,
        "price": 	7850	,
        "image": 	"REMEMONS.jpeg",	
        "imageDetail": [		
        	{ "id": 1, "url": "REMEMONS.jpeg" },	
        	{ "id": 2, "url": "REMEMONS1.jpeg" },	
        	{ "id": 3, "url": "REMEMONS2.jpeg" }	
        	],	
        "categoryId": 	2	
        },		



      {		
        "id": 	30	,
        "name": 	"top GIRL POWER",	
        "description": 	"👀🫦",	
        "price": 	6350	,
        "image": 	"TopGirlPower.jpg"	,
        "imageDetail": [		
          { "id": 1, "url": "TopGirlPower.jpg" },	
          { "id": 2, "url": "TopGirlPower2.jpg" },	
          { "id": 3, "url": "logo.png" }	
          ],	
        "categoryId": 	3	
        },		

        {		
        "id": 	31	,
        "name": 	"top NETX",	
        "description": 	"➡️➡️",	
        "price": 	4700	,
        "image": 	"TopNext.png"	,
        "imageDetail": [		
          { "id": 1, "url": "TopNext.png" },	
          { "id": 2, "url": "logo.png" },	
          { "id": 3, "url": "logo.png" }	
          ],	
        "categoryId": 	3	
        },		


        {		
        "id": 	32	,
        "name": 	"TOP KIKA",	
        "description": 	"",	
        "price": 	7350	,
        "image": 	"TopKika.webp"	,
        "imageDetail": [		
          { "id": 1, "url": "TopKika.webp" },	
          { "id": 2, "url": "TopKika2.webp" },	
          { "id": 3, "url": "logo.png" }	
          ],	
        "categoryId": 	3	
        },		


        {		
        "id": 	33	,
        "name": 	"TOP REFLEC",	
        "description": 	"MEDIDAS APROXIMADAS (las medidas son tomadas con la prenda plana), Largo: 39cm ,Ancho: 32cm",
        "price": 	9250	,
        "image": 	"TopReflex.webp"	,
        "imageDetail": [		
          { "id": 1, "url": "TopReflex.webp" },	
          { "id": 2, "url": "TopReflex2.webp" },	
          { "id": 3, "url": "TopReflex3.webp" }	
          ],	
        "categoryId": 	3	
        },		


        {		
        "id": 	34	,
        "name": 	"TOP REALLY",	
        "description": 	"Medidas Aproximadas, Largo: 30 cm ,Ancho: 32 cm",	
        "price": 	4950	,
        "image": 	"TopReally.jpeg"	,
        "imageDetail": [		
          { "id": 1, "url": "TopReally.jpeg" },	
          { "id": 2, "url": "TopReally1.webp" },	
          { "id": 3, "url": "TopReally3.webp" }	
          ],	
        "categoryId": 	3	
        },		

        {		
        "id": 	35	,
        "name": 	"TOP TOKIO",	
        "description": 	"Medidas Aproximadas, Largo: 35 cm, Ancho: 36 cm, Mangas: 16 cm",	
        "price": 	3900	,
        "image": 	"TopTokio.jpeg"	,
        "imageDetail": [		
          { "id": 1, "url": "TopTokio.jpeg" },	
          { "id": 2, "url": "TopTokio2.jpeg" },	
          { "id": 3, "url": "TopTokio3.webp" }	
          ],	
        "categoryId": 	3	
        },		
        			
      {			
        "id": 	36	,	
        "name": 	"TOP RAIZ",		
        "description": 	"Black or White"	,	
        "price": 	5000	,	
        "image": 	"TOPRAIZ.jpeg",		
        "imageDetail": [			
          { "id": 1, "url": "TOPRAIZ.jpeg" },		
          { "id": 3, "url": "logo.png" }	,	
          { "id": 3, "url": "logo.png" }		
          ],		
        "categoryId": 	3	
        },			
      
      {		
        "id": 	40	,
        "name": 	"BUZO ATACKK",	
        "description": 	"Buzo algodon frisado",	
        "price": 	12900	,
        "image": 	 "BuzoAtackk.jpg"	,
        "imageDetail": [		
          { "id": 1, "url": "BuzoAtackk.jpg" },	
          { "id": 2, "url": "BuzoAtackk2.jpg" },	
          { "id": 3, "url": "TalleBuzosPanic.png" }	
          ],	
        "categoryId": 	4	
        },		
            
        {		
        "id": 	41	,
        "name": 	"BUZO SKY",	
        "description": 	"Buzo algodon frisado",	
        "price": 	11000	,
        "image": 	"BuzoSky.jpg"	,
        "imageDetail": [		
          { "id": 1, "url": "BuzoSky.jpg" },	
          { "id": 2, "url": "BuzoSky2.jpg" },	
          { "id": 3, "url": "TalleBuzosPanic.png" }	
          ],	
        "categoryId": 	4	
        },		
            
            
            
        {		
        "id": 	42	,
        "name": 	"BUZO BLACK SKY",	
        "description": 	"Buzo algodon frisado",	
        "price": 	11000	,
        "image": 	"BuzoBlackSky.jpg"	,
        "imageDetail": [		
          { "id": 1, "url": "BuzoBlackSky.jpg" },	
          { "id": 2, "url": "BuzoBlackSky2.jpg" },	
          { "id": 3, "url": "TalleBuzosPanic.png" }	
          ],	
        "categoryId": 	4	
        },		
            
            
        {		
        "id": 	43	,
        "name": 	"BUZO WEIRD",	
        "description": 	"Buzo algodon frisado",	
        "price": 	12500	,
        "image": 	"BuzoWEIRD.jpeg"	,
        "imageDetail": [		
          { "id": 1, "url": "BuzoWEIRD.jpeg" },	
          { "id": 2, "url": "BuzoWEIRD2.jpeg" },	
          { "id": 3, "url": "TalleBuzosPanic.png" }	
          ],	
        "categoryId": 	4	
        },		
            
            
        {		
        "id": 	44	,
        "name": 	"BUZO CALABERA",	
        "description": 	"Buzo algodon frisado",	
        "price": 	12500	,
        "image": 	"Buzocalabera.jpeg"	,
        "imageDetail": [		
          { "id": 1, "url": "Buzocalabera.jpeg" },	
          { "id": 2, "url": "Buzocalabera2.jpeg" },	
          { "id": 3, "url": "TalleBuzosPanic.png" }	
          ],	
        "categoryId": 	4	
        },	
        
              {		
        "id": 	50	,
        "name": 	"PANTALON PARASHUTE",	
        "description": 	"talles 36 as 42"	,
        "price": 	14500	,
        "image": 	"PantaParashute.jpeg"	,
        "imageDetail": [		
          { "id": 1, "url": "PantaParashute.jpeg" },	
          { "id": 2, "url": "PantaParashute.jpg" },	
          { "id": 3, "url": "logo.png" }	
          ],	
        "categoryId": 	5
        },	

        {		
        "id": 	51	,
        "name": 	"FALDA RED SKIRT",	
        "description": 	"talles 36 al 38"	,
        "price": 	6900	,
        "image": 	"REDSKIRT.jpeg"	,
        "imageDetail": [		
          { "id": 1, "url": "REDSKIRT.jpeg" },	
          { "id": 2, "url": "logo.png" }	,
          { "id": 3, "url": "logo.png" }	
          ],	
        "categoryId": 	5
        },		


        {		
        "id": 	52	,
        "name": 	"PANTS GREYSA",	
        "description": 	"talles 36 al 42"	,
        "price": 	14900	,
        "image": 	"pantsGreysa.jpeg"	,
        "imageDetail": [		
          { "id": 1, "url": "pantsGreysa.jpeg" },	
          { "id": 2, "url": "logo.png" }	,
          { "id": 3, "url": "logo.png" }	
          ],	
        "categoryId": 	5
        },		


        {		
        "id": 	53	,
        "name": 	"PANTS CUADRILLE",	
        "description": 	"talles del S al XXXL",
        "price": 	24500	,
        "image": 	"PANTSCUADRILLE.jpeg"	,
        "imageDetail": [		
          { "id": 1, "url": "PANTSCUADRILLE.jpeg" },	
          { "id": 2, "url": "PANTSCUADRILLE2.jpeg" }	,
          { "id": 3, "url": "PANTSCUADRILLE3.jpeg" }	
          ],	
        "categoryId": 	5
        },		


        {		
        "id": 	54	,
        "name": 	"PANTS ZEBRA",	
        "description": 	"talles del S al XXXL"	,
        "price": 	24500	,
        "image": 	"PANTSZEBRA.jpeg"	,
        "imageDetail": [		
          { "id": 1, "url": "PANTSZEBRA.jpeg" },	
          { "id": 2, "url": "PANTSZEBRA2.jpeg" }	,
          { "id": 3, "url": "PANTSZEBRA3.jpeg" }	
          ],	
        "categoryId": 	5
        }


    ]


  }
  